subdomain_takeover_tools/__init__.py
subdomain_takeover_tools/authoritative_resolve.py
subdomain_takeover_tools/confirm_agile_crm.py
subdomain_takeover_tools/confirm_azure_api_management.py
subdomain_takeover_tools/confirm_azure_app_service.py
subdomain_takeover_tools/confirm_azure_edge_cdn.py
subdomain_takeover_tools/confirm_azure_traffic_manager.py
subdomain_takeover_tools/confirm_bigcartel.py
subdomain_takeover_tools/confirm_cargo.py
subdomain_takeover_tools/confirm_elb.py
subdomain_takeover_tools/confirm_fastly.py
subdomain_takeover_tools/confirm_github.py
subdomain_takeover_tools/confirm_godaddy.py
subdomain_takeover_tools/confirm_pantheon.py
subdomain_takeover_tools/confirm_s3.py
subdomain_takeover_tools/confirm_shopify.py
subdomain_takeover_tools/confirm_surge.py
subdomain_takeover_tools/confirm_takeover.py
subdomain_takeover_tools/confirm_tumblr.py
subdomain_takeover_tools/confirm_unclaimed.py
subdomain_takeover_tools/extract_domain_names.py
subdomain_takeover_tools/monitor_cnames.py
subdomain_takeover_tools/subtake_enrich_and_export.py
subdomain_takeover_tools/helper/load_token.py
subdomain_takeover_tools/helper/main.py
subdomain_takeover_tools/helper/prepare.py
subdomain_takeover_tools-0.47.0.dist-info/licenses/LICENSE
subdomain_takeover_tools-0.47.0.dist-info/METADATA
subdomain_takeover_tools-0.47.0.dist-info/WHEEL
subdomain_takeover_tools-0.47.0.dist-info/entry_points.txt
subdomain_takeover_tools-0.47.0.dist-info/top_level.txt
subdomain_takeover_tools-0.47.0.dist-info/RECORD
