Metadata-Version: 2.4
Name: subdomain_takeover_tools
Version: 0.47.0
Summary: Some helper subdomain_takeover_tools to validate subdomain takeovers
Home-page: https://github.com/martinvw/subdomain-takeover-tools
Author: Martin van Wingerden
Author-email: info@martinvw.nl
License: MIT
Keywords: subdomain-takeover,subtake,elb,s3,shopify
Classifier: Environment :: Console
Classifier: Intended Audience :: Developers
Classifier: Intended Audience :: System Administrators
Classifier: License :: OSI Approved :: MIT License
Classifier: Operating System :: POSIX :: Linux
Classifier: Programming Language :: Python :: 3.6
Classifier: Programming Language :: Python :: 3.7
Classifier: Programming Language :: Python :: 3.8
Classifier: Topic :: Scientific/Engineering :: Information Analysis
Classifier: Development Status :: 4 - Beta
Classifier: Topic :: Terminals
Classifier: Topic :: Utilities
License-File: LICENSE
Requires-Dist: tldextract
Requires-Dist: dnspython
Requires-Dist: boto3
Requires-Dist: azure-identity
Requires-Dist: azure-mgmt-trafficmanager
Provides-Extra: dev
Requires-Dist: bump; extra == "dev"
Dynamic: author
Dynamic: author-email
Dynamic: classifier
Dynamic: description
Dynamic: description-content-type
Dynamic: home-page
Dynamic: keywords
Dynamic: license
Dynamic: license-file
Dynamic: provides-extra
Dynamic: requires-dist
Dynamic: summary
